wespeakerruntime/__init__.py
wespeakerruntime/hub.py
wespeakerruntime/speaker.py
wespeakerruntime-1.0.1.dist-info/METADATA
wespeakerruntime-1.0.1.dist-info/WHEEL
wespeakerruntime-1.0.1.dist-info/top_level.txt
wespeakerruntime-1.0.1.dist-info/RECORD
