Metadata-Version: 2.1
Name: wespeakerruntime
Version: 1.0.1
Home-page: https://github.com/wenet-e2e/wespeaker
Author: Chengdong Liang
Author-email: liangchengdongd@qq.com
License: Apache licensed, as found in the LICENSE file
Classifier: Programming Language :: Python
Classifier: Topic :: Scientific/Engineering :: Artificial Intelligence
Requires-Python: >=3.6
Requires-Dist: onnxruntime
Requires-Dist: kaldiio
Requires-Dist: torchaudio
Requires-Dist: tqdm
